Metadata-Version: 2.1
Name: qwertyuiopl
Version: 1
Summary: Тест
Home-page: https://github.com/xllebbSQ/aiopayAPI
Author: tosterLIKE
Author-email: 090504opo@gmail.com
Classifier: Programming Language :: Python :: 3.8
Classifier: Programming Language :: Python :: 3.9
Classifier: Programming Language :: Python :: 3.10
Classifier: Programming Language :: Python :: 3.11
Classifier: License :: OSI Approved :: MIT License
Classifier: Operating System :: OS Independent
Requires-Python: >=3.8
